LICENSE
README.md
patch_ng.py
pyproject.toml
setup.py
patch_ng.egg-info/PKG-INFO
patch_ng.egg-info/SOURCES.txt
patch_ng.egg-info/dependency_links.txt
patch_ng.egg-info/top_level.txt