Metadata-Version: 2.1
Name: patch-ng
Version: 1.19.0
Summary: Library to parse and apply unified diffs.
Home-page: https://github.com/conan-io/python-patch
Author: Conan.io
Author-email: info@conan.io
License: MIT
Keywords: patch,parse,diff,strip,diffstat
Platform: UNKNOWN
Classifier: Development Status :: 5 - Production/Stable
Classifier: Intended Audience :: Developers
Classifier: Topic :: Software Development :: Build Tools
Classifier: License :: OSI Approved :: MIT License
Classifier: Programming Language :: Python :: 3
Classifier: Programming Language :: Python :: 3.6
Classifier: Programming Language :: Python :: 3.7
Classifier: Programming Language :: Python :: 3.8
Requires-Python: >=3.6
License-File: LICENSE
